making_with_code_cli/__init__.py
making_with_code_cli/cli.py
making_with_code_cli/curriculum.py
making_with_code_cli/decorators.py
making_with_code_cli/errors.py
making_with_code_cli/git_backend/__init__.py
making_with_code_cli/git_backend/base_backend.py
making_with_code_cli/git_backend/mwc_backend.py
making_with_code_cli/git_wrapper.py
making_with_code_cli/helpers.py
making_with_code_cli/mwc_accounts_api.py
making_with_code_cli/settings.py
making_with_code_cli/setup/__init__.py
making_with_code_cli/setup/tasks.py
making_with_code_cli/styles.py
making_with_code_cli/submit.py
making_with_code_cli/teach/__init__.py
making_with_code_cli/teach/assess.py
making_with_code_cli/teach/check/__init__.py
making_with_code_cli/teach/check/check_module.py
making_with_code_cli/teach/gitea_api/api.py
making_with_code_cli/teach/gitea_api/exceptions.py
making_with_code_cli/teach/log.py
making_with_code_cli/teach/patch.py
making_with_code_cli/teach/section/__init__.py
making_with_code_cli/teach/section/create.py
making_with_code_cli/teach/section/delete.py
making_with_code_cli/teach/section/edit.py
making_with_code_cli/teach/section/show.py
making_with_code_cli/teach/setup.py
making_with_code_cli/teach/status.py
making_with_code_cli/teach/student/__init__.py
making_with_code_cli/teach/student/create.py
making_with_code_cli/teach/student/update.py
making_with_code_cli/teach/student_repo_functions.py
making_with_code_cli/teach/student_repos.py
making_with_code_cli/teach/update.py
making_with_code_cli/update/__init__.py
making_with_code_cli/version.py
making_with_code_cli-5.1.0.dist-info/WHEEL
making_with_code_cli-5.1.0.dist-info/entry_points.txt
making_with_code_cli-5.1.0.dist-info/METADATA
making_with_code_cli-5.1.0.dist-info/RECORD
