Metadata-Version: 2.3
Name: making-with-code-cli
Version: 5.1.0
Summary: Courseware for Making With Code
Author: Chris Proctor
Author-email: Chris Proctor <chris@chrisproctor.net>
License: MIT
Classifier: Programming Language :: Python :: 3
Classifier: Programming Language :: Python :: 3.11
Classifier: Programming Language :: Python :: 3.12
Classifier: Programming Language :: Python :: 3.13
Classifier: Programming Language :: Python :: 3.14
Requires-Dist: pyyaml>=6.0.2,<7.0.0
Requires-Dist: click>=8.1.8,<9.0.0
Requires-Dist: requests>=2.32.3,<3.0.0
Requires-Dist: tabulate>=0.9.0,<0.10.0
Requires-Dist: gitpython>=3.1.44,<4.0.0
Requires-Dist: dateparser>=1.2.0,<2.0.0
Requires-Dist: tqdm>=4.67.1,<5.0.0
Requires-Dist: tomlkit>=0.14.0
Requires-Python: >=3.11, <4.0
Project-URL: documentation, https://docs.makingwithcode.org/making-with-code-cli
Project-URL: issues, https://github.com/cproctor/making-with-code-courseware/issues
